{
  "fields": [
    {
      "key": "heroImg1",
      "type": "Image",
      "label": "* Image (desktop)",
      "groupId": "heroBanner1",
      "required": true,
      "description": "Hero banner (new) desktop image"
    },
    {
      "key": "heroImgM1",
      "type": "Image",
      "label": "* Image (mobile)",
      "groupId": "heroBanner1",
      "required": true,
      "description": "Hero banner (new) mobile image"
    },
    {
      "key": "heroPreTitle1",
      "type": "String",
      "label": "Pre-title text",
      "groupId": "heroBanner1",
      "required": false,
      "description": "Pre-title text for the hero banner (new)"
    },
    {
      "key": "heroTitle1",
      "type": "String",
      "label": "Title (large text)",
      "groupId": "heroBanner1",
      "required": false,
      "description": "Large title text for the hero banner (new)"
    },
    {
      "key": "heroTitleSmall1",
      "type": "String",
      "label": "Title (small text)",
      "groupId": "heroBanner1",
      "required": false,
      "description": "Small title text for the hero banner (new)"
    },
    {
      "key": "heroSmallPrint1",
      "type": "String",
      "label": "Small print",
      "groupId": "heroBanner1",
      "required": false,
      "description": "Small Print under title for the hero banner (new)"
    },
    {
      "key": "heroSuccessTitle1",
      "type": "String",
      "label": "Success Title",
      "groupId": "heroBanner1",
      "required": false,
      "description": "Title for the hero banner (new) after the form is submitted"
    },
    {
      "key": "heroSuccessText1",
      "type": "String",
      "label": "Success Text",
      "groupId": "heroBanner1",
      "required": false,
      "description": "Text for the hero banner (new) after the form is submitted"
    },
    {
      "key": "heroContent1_primary_colour",
      "type": "String",
      "label": "Primary text colour (desktop)",
      "groupId": "heroBanner1",
      "required": false,
      "description": "HEX code for the primary text colour on desktop"
    },
    {
      "key": "heroContent1_secondary_colour",
      "type": "String",
      "label": "Secondary text colour (desktop)",
      "groupId": "heroBanner1",
      "required": false,
      "description": "HEX code for the secondary text colour on desktop"
    },
    {
      "key": "heroContent1_primary_colour_mob",
      "type": "String",
      "label": "Primary text colour (mobile)",
      "groupId": "heroBanner1",
      "required": false,
      "description": "HEX code for the primary text colour on mobile"
    },
    {
      "key": "heroContent1_secondary_colour_mob",
      "type": "String",
      "label": "Secondary text colour (mobile)",
      "groupId": "heroBanner1",
      "required": false,
      "description": "HEX code for the secondary text colour on mobile"
    },
    {
      "key": "heroCtaText1",
      "type": "String",
      "label": "* CTA text",
      "groupId": "heroBanner1",
      "required": true
    },
    {
      "key": "heroCta1_bg_colour",
      "type": "String",
      "label": "CTA background colour (desktop)",
      "groupId": "heroBanner1",
      "required": false,
      "description": "HEX"
    },
    {
      "key": "heroCta1_bg_colour_mob",
      "type": "String",
      "label": "CTA background colour (mobile)",
      "groupId": "heroBanner1",
      "required": false,
      "description": "HEX"
    },
    {
      "key": "heroCta1_text_colour",
      "type": "String",
      "label": "CTA text colour (desktop)",
      "groupId": "heroBanner1",
      "required": false,
      "description": "HEX"
    },
    {
      "key": "heroCta1_text_colour_mob",
      "type": "String",
      "label": "CTA text colour (mobile)",
      "groupId": "heroBanner1",
      "required": false,
      "description": "HEX"
    },
    {
      "key": "heroTerms1",
      "type": "String",
      "label": "Ts&Cs text",
      "groupId": "heroBanner1",
      "required": false,
      "description": "Ts&Cs Text (excluding the link) for Desktop (use '\\n' for line break)"
    },
    {
      "key": "heroContent1_side",
      "type": "String",
      "label": "Banner content side (desktop)",
      "groupId": "heroBanner1",
      "required": false,
      "description": "left/right"
    },
    {
      "key": "heroContent1_side_offset",
      "type": "String",
      "label": "Banner content side offset (desktop)",
      "groupId": "heroBanner1",
      "required": false,
      "description": "Specify the banner content offset from the left/right side (depending on the side chosen above). use px/pt"
    },
    {
      "key": "heroContent1_bottom",
      "type": "String",
      "label": "Banner content bottom offset (desktop)",
      "groupId": "heroBanner1",
      "required": false,
      "description": "px/pt"
    },
    {
      "key": "heroImg1b",
      "type": "Image",
      "label": "* Image (desktop)",
      "groupId": "heroBanner1b",
      "required": true,
      "description": "Hero banner (returning) desktop image"
    },
    {
      "key": "heroImgM1b",
      "type": "Image",
      "label": "* Image (mobile)",
      "groupId": "heroBanner1b",
      "required": true,
      "description": "Hero banner (returning) mobile image"
    },
    {
      "key": "heroHref1b",
      "type": "URL",
      "label": "* Link URL",
      "groupId": "heroBanner1b",
      "required": true,
      "description": "Link for the hero banner (returning)"
    },
    {
      "key": "heroTitle1b",
      "type": "String",
      "label": "Title",
      "groupId": "heroBanner1b",
      "required": false,
      "description": "Title text for the hero banner (returning)"
    },
    {
      "key": "heroOfferCode1b",
      "type": "String",
      "label": "Offer Code",
      "groupId": "heroBanner1b",
      "required": false,
      "description": "Offer code copy for hero banner (returning)"
    },
    {
      "key": "heroContent1b_primary_colour",
      "type": "String",
      "label": "Primary text colour (desktop)",
      "groupId": "heroBanner1b",
      "required": false,
      "description": "HEX code for the primary text colour on desktop"
    },
    {
      "key": "heroContent1b_secondary_colour",
      "type": "String",
      "label": "Secondary text colour (desktop)",
      "groupId": "heroBanner1b",
      "required": false,
      "description": "HEX code for the secondary text colour on desktop"
    },
    {
      "key": "heroContent1b_primary_colour_mob",
      "type": "String",
      "label": "Primary text colour (mobile)",
      "groupId": "heroBanner1b",
      "required": false,
      "description": "HEX code for the primary text colour on mobile"
    },
    {
      "key": "heroContent1b_secondary_colour_mob",
      "type": "String",
      "label": "Secondary text colour (mobile)",
      "groupId": "heroBanner1b",
      "required": false,
      "description": "HEX code for the secondary text colour on mobile"
    },
    {
      "key": "heroCtaText1b",
      "type": "String",
      "label": "CTA text",
      "groupId": "heroBanner1b",
      "required": false
    },
    {
      "key": "heroCta1b_bg_colour",
      "type": "String",
      "label": "CTA background colour (desktop)",
      "groupId": "heroBanner1b",
      "required": false,
      "description": "HEX"
    },
    {
      "key": "heroCta1b_bg_colour_mob",
      "type": "String",
      "label": "CTA background colour (mobile)",
      "groupId": "heroBanner1b",
      "required": false,
      "description": "HEX"
    },
    {
      "key": "heroCta1b_text_colour",
      "type": "String",
      "label": "CTA text colour (desktop)",
      "groupId": "heroBanner1b",
      "required": false,
      "description": "HEX"
    },
    {
      "key": "heroCta1b_text_colour_mob",
      "type": "String",
      "label": "CTA text colour (mobile)",
      "groupId": "heroBanner1b",
      "required": false,
      "description": "HEX"
    },
    {
      "key": "heroCtaShow1b",
      "type": "Boolean",
      "label": "Show CTA on desktop banner (returning)",
      "groupId": "heroBanner1b",
      "required": false,
      "description": "Check this box to show CTA on desktop banner (returning)"
    },
    {
      "key": "heroTerms1b",
      "type": "String",
      "label": "Ts&Cs text",
      "groupId": "heroBanner1b",
      "required": false,
      "description": "Ts&Cs Text (excluding the link) for Desktop (use '\\n' for line break)"
    },
    {
      "key": "heroContent1b_side",
      "type": "String",
      "label": "Banner content side (desktop)",
      "groupId": "heroBanner1b",
      "required": false,
      "description": "left/right"
    },
    {
      "key": "heroContent1b_side_offset",
      "type": "String",
      "label": "Banner content side offset (desktop)",
      "groupId": "heroBanner1b",
      "required": false,
      "description": "Specify the banner content offset from the left/right side (depending on the side chosen above). use px/pt"
    },
    {
      "key": "heroContent1b_bottom",
      "type": "String",
      "label": "Banner content bottom offset (desktop)",
      "groupId": "heroBanner1b",
      "required": false,
      "description": "px/pt"
    },
    {
      "key": "heroImg2",
      "type": "Image",
      "label": "* Image (desktop)",
      "groupId": "heroBanner2",
      "required": true,
      "description": "Hero banner desktop image"
    },
    {
      "key": "heroImgM2",
      "type": "Image",
      "label": "* Image (mobile)",
      "groupId": "heroBanner2",
      "required": true,
      "description": "Hero banner mobile image"
    },
    {
      "key": "heroHref2",
      "type": "URL",
      "label": "* Link URL",
      "groupId": "heroBanner2",
      "required": true,
      "description": "Where the hero banner banner should link to"
    },
    {
      "key": "heroPreTitle2",
      "type": "String",
      "label": "Pre-title text",
      "groupId": "heroBanner2",
      "required": false,
      "description": "Pre-title text for the hero banner"
    },
    {
      "key": "heroTitle2",
      "type": "String",
      "label": "Title",
      "groupId": "heroBanner2",
      "required": false,
      "description": "Title for the hero banner"
    },
    {
      "key": "heroCode2",
      "type": "String",
      "label": "Code text",
      "groupId": "heroBanner2",
      "required": false,
      "description": "Code text under hero title"
    },
    {
      "key": "heroContent2_primary_colour",
      "type": "String",
      "label": "Primary text colour (desktop)",
      "groupId": "heroBanner2",
      "required": false,
      "description": "HEX code for the primary text colour on desktop"
    },
    {
      "key": "heroContent2_secondary_colour",
      "type": "String",
      "label": "Secondary text colour (desktop)",
      "groupId": "heroBanner2",
      "required": false,
      "description": "HEX code for the secondary text colour on desktop"
    },
    {
      "key": "heroContent2_primary_colour_mob",
      "type": "String",
      "label": "Primary text colour (mobile)",
      "groupId": "heroBanner2",
      "required": false,
      "description": "HEX code for the primary text colour on mobile"
    },
    {
      "key": "heroContent2_secondary_colour_mob",
      "type": "String",
      "label": "Secondary text colour (mobile)",
      "groupId": "heroBanner2",
      "required": false,
      "description": "HEX code for the secondary text colour on mobile"
    },
    {
      "key": "heroCtaText2",
      "type": "String",
      "label": "* CTA text",
      "groupId": "heroBanner2",
      "required": true
    },
    {
      "key": "heroCta2_bg_colour",
      "type": "String",
      "label": "CTA background colour (desktop)",
      "groupId": "heroBanner2",
      "required": false,
      "description": "HEX"
    },
    {
      "key": "heroCta2_bg_colour_mob",
      "type": "String",
      "label": "CTA background colour (mobile)",
      "groupId": "heroBanner2",
      "required": false,
      "description": "HEX"
    },
    {
      "key": "heroCta2_text_colour",
      "type": "String",
      "label": "CTA text colour (desktop)",
      "groupId": "heroBanner2",
      "required": false,
      "description": "HEX"
    },
    {
      "key": "heroCta2_text_colour_mob",
      "type": "String",
      "label": "CTA text colour (mobile)",
      "groupId": "heroBanner2",
      "required": false,
      "description": "HEX"
    },
    {
      "key": "heroTerms2",
      "type": "String",
      "label": "Ts&Cs text",
      "groupId": "heroBanner2",
      "required": false,
      "description": "Ts&Cs Text (excluding the link) for Desktop (use '\\n' for line break)"
    },
    {
      "key": "heroContent2_side",
      "type": "String",
      "label": "Banner content side (desktop)",
      "groupId": "heroBanner2",
      "required": false,
      "description": "left/right"
    },
    {
      "key": "heroContent2_side_offset",
      "type": "String",
      "label": "Banner content side offset (desktop)",
      "groupId": "heroBanner2",
      "required": false,
      "description": "Specify the Offer Code offset from the left/right side (depending on the Offer code side chosen above). use px/pt"
    },
    {
      "key": "heroContent2_bottom",
      "type": "String",
      "label": "Banner content bottom offset (desktop)",
      "groupId": "heroBanner2",
      "required": false,
      "description": "px/pt"
    }
  ],
  "groups": [
    {
      "id": "heroBanner1",
      "title": "Hero Banner 1 - New Users (* required field)",
      "subtitle": "Use the information below to customise the new user hero banner."
    },
    {
      "id": "heroBanner1b",
      "title": "Hero Banner 1b - Returning Users (* required field)",
      "subtitle": "Use the information below to customise the returning user hero banner."
    },
    {
      "id": "heroBanner2",
      "title": "Hero Banner 2 (* required field)",
      "subtitle": "Use the information below to customise the hero banner."
    }
  ]
}